ptb_firebase_persistence/__init__.py
ptb_firebase_persistence/firebase_persistence.py
ptb_firebase_persistence-0.1.2.dist-info/WHEEL
ptb_firebase_persistence-0.1.2.dist-info/METADATA
ptb_firebase_persistence-0.1.2.dist-info/RECORD
