Metadata-Version: 2.1
Name: ptb-firebase-persistence
Version: 0.1.2
Summary: 
Home-page: https://github.com/licht1stein/ptb-firebase-persistence
Author: Mikhail Beliansky
Author-email: mb@blaster.ai
Requires-Python: >=3.7,<4.0
Classifier: Programming Language :: Python :: 3
Classifier: Programming Language :: Python :: 3.7
Classifier: Programming Language :: Python :: 3.8
Requires-Dist: firebase-admin (>=4.3.0,<5.0.0)
